{
  "reactjs": "React",
  "react.js": "React",
  "react": "React",
  "node.js": "Node.js",
  "nodejs": "Node.js",
  "node": "Node.js",
  "py": "Python",
  "python": "Python",
  "python3": "Python",
  "js": "JavaScript",
  "javascript": "JavaScript",
  "ts": "TypeScript",
  "typescript": "TypeScript",
  "c++": "C++",
  "cpp": "C++",
  "c#": "C#",
  "csharp": "C#",
  ".net": ".NET",
  "dotnet": ".NET",
  "golang": "Go",
  "go": "Go",
  "k8s": "Kubernetes",
  "kubernetes": "Kubernetes",
  "postgres": "PostgreSQL",
  "postgresql": "PostgreSQL",
  "tf": "TensorFlow",
  "tensorflow": "TensorFlow",
  "java": "Java",
  "springboot": "Spring Boot",
  "spring": "Spring",
  "aws": "AWS",
  "sql": "SQL",
  "docker": "Docker",
  "ruby": "Ruby",
  "rails": "Ruby on Rails",
  "ruby on rails": "Ruby on Rails",
  "ror": "Ruby on Rails",
  "vue": "Vue.js",
  "vue.js": "Vue.js",
  "vuejs": "Vue.js",
  "angular": "Angular",
  "angularjs": "Angular",
  "svelte": "Svelte",
  "next": "Next.js",
  "next.js": "Next.js",
  "nextjs": "Next.js",
  "rust": "Rust",
  "kotlin": "Kotlin",
  "scala": "Scala",
  "swift": "Swift",
  "php": "PHP",
  "graphql": "GraphQL",
  "mongodb": "MongoDB",
  "mongo": "MongoDB",
  "redis": "Redis",
  "mysql": "MySQL",
  "terraform": "Terraform",
  "gcp": "GCP",
  "azure": "Azure",
  "tailwind": "Tailwind CSS",
  "tailwindcss": "Tailwind CSS",
  "pytorch": "PyTorch",
  "torch": "PyTorch",
  "django": "Django",
  "flask": "Flask",
  "fastapi": "FastAPI",
  "elasticsearch": "Elasticsearch",
  "kafka": "Kafka",
  "spark": "Apache Spark"
}
